LICENSE
README.md
setup.py
jax_gnn/__init__.py
jax_gnn.egg-info/PKG-INFO
jax_gnn.egg-info/SOURCES.txt
jax_gnn.egg-info/dependency_links.txt
jax_gnn.egg-info/requires.txt
jax_gnn.egg-info/top_level.txt
jax_gnn/data/__init__.py
jax_gnn/data/dataset.py
jax_gnn/data/graph.py
jax_gnn/datasets/__init__.py
jax_gnn/datasets/planetoid.py
jax_gnn/nn/__init__.py
jax_gnn/nn/conv/__init__.py
jax_gnn/nn/conv/gcn.py
jax_gnn/utils/__init__.py
jax_gnn/utils/data_utils.py
jax_gnn/utils/graph_utils.py
jax_gnn/utils/jax_utils.py